myaskaipy/__init__.py
myaskaipy/example.py
myaskai_py-1.0.4.dist-info/LICENSE
myaskai_py-1.0.4.dist-info/METADATA
myaskai_py-1.0.4.dist-info/WHEEL
myaskai_py-1.0.4.dist-info/top_level.txt
myaskai_py-1.0.4.dist-info/RECORD
