Metadata-Version: 2.1
Name: myaskai_py
Version: 1.0.4
Summary: A small example package
Author-email: Alex <Alexrainey00@gmail.com>
Project-URL: Homepage, https://github.com/arainey2022/myaskai-py
Project-URL: Issues, https://github.com/arainey2022/myaskai-py/issues
Classifier: Programming Language :: Python :: 3
Classifier: License :: OSI Approved :: MIT License
Classifier: Operating System :: OS Independent
Requires-Python: >=3.8
License-File: LICENSE
